thlink_backend_test_lib/__init__.py
thlink_backend_test_lib/pytest_mock_fixtures.py
thlink_backend_test_lib/utils.py
thlink_backend_test_lib-0.2.5.dist-info/entry_points.txt
thlink_backend_test_lib-0.2.5.dist-info/LICENSE
thlink_backend_test_lib-0.2.5.dist-info/WHEEL
thlink_backend_test_lib-0.2.5.dist-info/METADATA
thlink_backend_test_lib-0.2.5.dist-info/RECORD
