Metadata-Version: 2.1
Name: thlink-backend-test-lib
Version: 0.2.5
Summary: pytest mock fixtures
Author: thlink
Requires-Python: >=3.7,<4.0
Classifier: Programming Language :: Python :: 3
Classifier: Programming Language :: Python :: 3.7
Classifier: Programming Language :: Python :: 3.8
Classifier: Programming Language :: Python :: 3.9
Requires-Dist: aws-lambda-powertools (>=1.16.1,<2.0.0)
Requires-Dist: pytest (>=6.2.4,<7.0.0)
Requires-Dist: thlink-backend-app-lib (>=0.6.0,<0.7.0)
Requires-Dist: thlink-backend-db-lib (>=0.4.0,<0.5.0)
Requires-Dist: thlink-backend-notification-lib (>=0.6.0,<0.7.0)
Requires-Dist: thlink-backend-object-storage-lib (>=0.2.1,<0.3.0)
